{"nodes":[
  {"name":"Australië"},
  {"name":"Brazilië"},
  {"name":"Canada"},
  {"name":"Denemarken"},
  {"name":"China"},
  {"name":"Frankrijk"},
  {"name":"Duitsland"},
  {"name":"India"},
  {"name":"Ierland"},
  {"name":"Israël"},
  {"name":"Italië"},
  {"name":"Maleisië"},
  {"name":"Portugal"},
  {"name":"Saudie Arabië"},
  {"name":"Singapore"},
  {"name":"Zuid-Afrika"},
  {"name":"Zuid-Korea"},
  {"name":"Zweden"},
  {"name":"Zwitserland"},
  {"name":"VAE"},
  {"name":"Groot-Brittanië"},
  {"name":"Verenigde Staten"},
  {"name":"[onbekend]"},
  {"name":"Nieuw Zeeland"},
  {"name":"Congo"},
  {"name":"Ethiopië"},
  {"name":"Argentinië"},
  {"name":"Roemenië"},
  {"name":"Paraguay"},
  {"name":"Uruguay"},
  {"name":"Slowakije"},
  {"name":"Indonesië"},
  {"name":"Polen"},
  {"name":"Rusland"},
  {"name":"Nigerië"},
  {"name":"Mozambique"},
  {"name":"Soedan"},
  {"name":"Ghana"},
  {"name":"Filippijnen"},
  {"name":"Guinee"},
  {"name":"Swaziland"},
  {"name":"Tanzania"},
  {"name":"Zambia"},
  {"name":"Zimbabwe"},
  {"name":"Bulgarije"},
  {"name":"Mali"},
  {"name":"Zuid-Soedan"}
],
  "links":[
    {"source": 26 ,"target": 1 ,"value": 455 },
    {"source": 1 ,"target": 0 ,"value": 1876 },
    {"source": 2 ,"target": 1 ,"value": 97124 },
    {"source": 4 ,"target": 0 ,"value": 1708 },
    {"source": 4 ,"target": 24 ,"value": 2800000 },
    {"source": 4 ,"target": 25 ,"value": 115182 },
    {"source": 4 ,"target": 23 ,"value": 8615 },
    {"source": 4 ,"target": 33 ,"value": 426667 },
    {"source": 3 ,"target": 26 ,"value": 12433 },
    {"source": 3 ,"target": 23 ,"value": 14461 },
    {"source": 3 ,"target": 27 ,"value": 8632 },
    {"source": 3 ,"target": 33 ,"value": 120626 },
    {"source": 3 ,"target": 21 ,"value": 1427 },
    {"source": 5 ,"target": 26 ,"value": 5810 },
    {"source": 5 ,"target": 1 ,"value": 61681 },
    {"source": 5 ,"target": 28 ,"value": 2859 },
    {"source": 5 ,"target": 29 ,"value": 13618 },
    {"source": 6 ,"target": 23 ,"value": 1473 },
    {"source": 6 ,"target": 30 ,"value": 5167 },
    {"source": 7 ,"target": 31 ,"value": 2079847 },
    {"source": 8 ,"target": 32 ,"value": 1119 },
    {"source": 9 ,"target": 24 ,"value": 2000000 },
    {"source": 10 ,"target": 23 ,"value": 16666 },
    {"source": 10 ,"target": 34 ,"value": 11292 },
    {"source": 11 ,"target": 31 ,"value": 643397 },
    {"source": 12 ,"target": 1 ,"value": 29528 },
    {"source": 12 ,"target": 35 ,"value": 24234 },
    {"source": 12 ,"target": 27 ,"value": 25244 },
    {"source": 13 ,"target": 26 ,"value": 12506 },
    {"source": 13 ,"target": 36 ,"value": 9407 },
    {"source": 14 ,"target": 37 ,"value": 6157 },
    {"source": 14 ,"target": 31 ,"value": 139814 },
    {"source": 15 ,"target": 35 ,"value": 1031178 },
    {"source": 16 ,"target": 26 ,"value": 20894 },
    {"source": 16 ,"target": 38 ,"value": 100011 },
    {"source": 17 ,"target": 32 ,"value": 6705 },
    {"source": 18 ,"target": 23 ,"value": 8484 },
    {"source": 19 ,"target": 36 ,"value": 1500105 },
    {"source": 20 ,"target": 0 ,"value": 3200047 },
    {"source": 20 ,"target": 39 ,"value": 106415 },
    {"source": 20 ,"target": 33 ,"value": 33870 },
    {"source": 20 ,"target": 40 ,"value": 1386 },
    {"source": 20 ,"target": 41 ,"value": 5818 },
    {"source": 20 ,"target": 42 ,"value": 2533 },
    {"source": 20 ,"target": 43 ,"value": 9913 },
    {"source": 22 ,"target": 24 ,"value": 3000000 },
    {"source": 22 ,"target": 31 ,"value": 3091434 },
    {"source": 22 ,"target": 41 ,"value": 20309 },
    {"source": 21 ,"target": 44 ,"value": 29438 },
    {"source": 21 ,"target": 37 ,"value": 4364 },
    {"source": 21 ,"target": 45 ,"value": 22471 },
    {"source": 21 ,"target": 46 ,"value": 1000 },
    {"source": 21 ,"target": 41 ,"value": 80562 }
  ]}
